metas_unclib/Metas.Alglib.dll
metas_unclib/Metas.IntelMKL.dll
metas_unclib/Metas.IntelMKL.dll.config
metas_unclib/Metas.UncLib.Core.dll
metas_unclib/Metas.UncLib.DistProp.dll
metas_unclib/Metas.UncLib.LinProp.dll
metas_unclib/Metas.UncLib.MCProp.dll
metas_unclib/Metas.UncLib.Optimization.dll
metas_unclib/Microsoft.VisualStudio.DebuggerVisualizers.dll
metas_unclib/__init__.py
metas_unclib/metas_unclib.py
metas_unclib/doc/MetasUncLibDataFormats.pdf
metas_unclib/doc/MetasUncLibDataFormats.xsd
metas_unclib/doc/MetasUncLibPython.pdf
metas_unclib/examples/__init__.py
metas_unclib/examples/eigenvalue.py
metas_unclib/examples/gum_h1.py
metas_unclib/examples/gum_h2.py
metas_unclib/examples/gum_h3.py
metas_unclib/examples/gum_h4.py
metas_unclib/examples/integrate.py
metas_unclib/examples/interpolation.py
metas_unclib/examples/nonlin_linprop_and_mcprop.py
metas_unclib/examples/numerical_step.py
metas_unclib/examples/ode_solver.py
metas_unclib/examples/optimizer.py
metas_unclib/examples/resistor_cube.py
metas_unclib/examples/right_triangle.py
metas_unclib/examples/right_triangle_linprop_and_mcprop.py
metas_unclib/examples/roots.py
metas_unclib/examples/storage_performance.py
metas_unclib/mkl_custom/win/ia32/custom_mkl.dll
metas_unclib/mkl_custom/win/ia32/custom_mkl.dll.manifest
metas_unclib/mkl_custom/win/ia32/custom_mkl.exp
metas_unclib/mkl_custom/win/ia32/custom_mkl.lib
metas_unclib/mkl_custom/win/ia32/libiomp5md.dll
metas_unclib-2.9.4.dist-info/LICENSE
metas_unclib-2.9.4.dist-info/METADATA
metas_unclib-2.9.4.dist-info/WHEEL
metas_unclib-2.9.4.dist-info/top_level.txt
metas_unclib-2.9.4.dist-info/RECORD
